backports/configparser/__init__.py
backports/configparser/compat.py
configparser-7.1.0.dist-info/LICENSE
configparser-7.1.0.dist-info/METADATA
configparser-7.1.0.dist-info/WHEEL
configparser-7.1.0.dist-info/top_level.txt
configparser-7.1.0.dist-info/RECORD
